Metadata-Version: 2.1
Name: Rickrack
Version: 2.8.35
Summary: Generate harmonious colors freely.
Home-page: https://eigenmiao.com/rickrack/
Author: Eigenmiao
Author-email: eigenmiao@outlook.com
License: UNKNOWN
Keywords: Color-Editor,Color-Picker,Color-Palette,Digital-Palette,Desktop-Application
Platform: UNKNOWN
Classifier: Topic :: Multimedia :: Graphics
Classifier: Topic :: Utilities
Classifier: Development Status :: 5 - Production/Stable
Classifier: License :: OSI Approved :: GNU General Public License v3 (GPLv3)
Classifier: Programming Language :: Python :: 3
Classifier: Operating System :: Microsoft :: Windows
Classifier: Operating System :: POSIX
Classifier: Environment :: X11 Applications
Classifier: Intended Audience :: End Users/Desktop
Classifier: Intended Audience :: Other Audience
Classifier: Natural Language :: Chinese (Simplified)
Classifier: Natural Language :: English
Requires-Python: >=3.5
